ci/transparency/sdk/__init__.py
ci/transparency/sdk/_version.py
ci/transparency/sdk/digests.py
ci/transparency/sdk/hash_core.py
ci/transparency/sdk/ids.py
ci/transparency/sdk/io_schema.py
ci/transparency/sdk/window_agg.py
ci/transparency/sdk/cli/main.py
civic_transparency_sdk-0.1.2.data/data/share/civic-transparency-ptag-spec/CITATION.cff
civic_transparency_sdk-0.1.2.data/data/share/civic-transparency-ptag-spec/LICENSE
civic_transparency_sdk-0.1.2.data/data/share/civic-transparency-ptag-spec/README.md
civic_transparency_sdk-0.1.2.dist-info/licenses/LICENSE
civic_transparency_sdk-0.1.2.dist-info/METADATA
civic_transparency_sdk-0.1.2.dist-info/WHEEL
civic_transparency_sdk-0.1.2.dist-info/entry_points.txt
civic_transparency_sdk-0.1.2.dist-info/top_level.txt
civic_transparency_sdk-0.1.2.dist-info/RECORD
