Metadata-Version: 2.4
Name: civic-transparency-sdk
Version: 0.1.2
Summary: Civic Transparency SDK - Development kit for transparency applications
Author: Civic Interconnect
License-Expression: MIT
Project-URL: Bug Tracker, https://github.com/civic-interconnect/civic-transparency-py-sdk/issues
Project-URL: Documentation, https://civic-interconnect.github.io/civic-transparency-py-sdk/latest/
Project-URL: Homepage, https://github.com/civic-interconnect/civic-transparency-py-sdk
Project-URL: Repository, https://github.com/civic-interconnect/civic-transparency-py-sdk
Keywords: transparency,api,sdk,civic
Classifier: Development Status :: 3 - Alpha
Classifier: Intended Audience :: Developers
Classifier: Intended Audience :: Science/Research
Classifier: Intended Audience :: Education
Classifier: Operating System :: OS Independent
Classifier: Programming Language :: Python :: 3
Classifier: Programming Language :: Python :: 3 :: Only
Classifier: Programming Language :: Python :: 3.12
Classifier: Programming Language :: Python :: 3.13
Classifier: Topic :: Scientific/Engineering
Classifier: Topic :: Software Development :: Libraries :: Python Modules
Requires-Python: >=3.12
License-File: LICENSE
Requires-Dist: defusedxml
Requires-Dist: duckdb
Requires-Dist: orjson
Requires-Dist: typer
Provides-Extra: dev
Requires-Dist: bandit; extra == "dev"
Requires-Dist: build; extra == "dev"
Requires-Dist: defusedxml; extra == "dev"
Requires-Dist: deptry; extra == "dev"
Requires-Dist: jsonschema; extra == "dev"
Requires-Dist: pre-commit; extra == "dev"
Requires-Dist: pyright; extra == "dev"
Requires-Dist: pytest; extra == "dev"
Requires-Dist: pytest-cov; extra == "dev"
Requires-Dist: ruff; extra == "dev"
Requires-Dist: validate-pyproject; extra == "dev"
Provides-Extra: docs
Requires-Dist: mkdocs; extra == "docs"
Requires-Dist: mkdocs-gen-files; extra == "docs"
Requires-Dist: mkdocs-git-revision-date-localized-plugin; extra == "docs"
Requires-Dist: mkdocs-include-markdown-plugin; extra == "docs"
Requires-Dist: mkdocs-literate-nav; extra == "docs"
Requires-Dist: mkdocs-material; extra == "docs"
Requires-Dist: mkdocs-static-i18n; extra == "docs"
Requires-Dist: mkdocstrings[python]>=0.18; extra == "docs"
Requires-Dist: mike; extra == "docs"
Requires-Dist: setuptools-scm; extra == "docs"
Dynamic: license-file
